geko/__init__.py
geko/core.py
geko/curriculum.py
geko/partitioner.py
geko/trainer.py
gekolib-0.1.1.dist-info/licenses/LICENSE
gekolib-0.1.1.dist-info/METADATA
gekolib-0.1.1.dist-info/WHEEL
gekolib-0.1.1.dist-info/top_level.txt
gekolib-0.1.1.dist-info/RECORD
